setup.cfg
setup.py
matuamod_serializer/__init__.py
matuamod_serializer/__main__.py
matuamod_serializer.egg-info/PKG-INFO
matuamod_serializer.egg-info/SOURCES.txt
matuamod_serializer.egg-info/dependency_links.txt
matuamod_serializer.egg-info/top_level.txt
matuamod_serializer/converters/__init__.py
matuamod_serializer/converters/converters.py
matuamod_serializer/create_serializer/__init__.py
matuamod_serializer/create_serializer/create_serializer.py
matuamod_serializer/dto/__init__.py
matuamod_serializer/dto/dto.py
matuamod_serializer/parser/__init__.py
matuamod_serializer/parser/json_parser/__init__.py
matuamod_serializer/parser/json_parser/json_parser.py
matuamod_serializer/parser/parse_arguments/__init__.py
matuamod_serializer/parser/parse_arguments/parse_json_arguments.py
matuamod_serializer/parser/toml_parser/__init__.py
matuamod_serializer/parser/toml_parser/toml_parser.py
matuamod_serializer/parser/yaml_parser/__init__.py
matuamod_serializer/parser/yaml_parser/yaml_parser.py
matuamod_serializer/serializer/__init__.py
matuamod_serializer/serializer/base_serializer/__init__.py
matuamod_serializer/serializer/base_serializer/base_serializer.py
matuamod_serializer/serializer/dependencies/__init__.py
matuamod_serializer/serializer/dependencies/dependencies.py
matuamod_serializer/serializer/json_serializer/__init__.py
matuamod_serializer/serializer/json_serializer/json_serializer.py
matuamod_serializer/serializer/toml_serializer/__init__.py
matuamod_serializer/serializer/toml_serializer/toml_serializer.py
matuamod_serializer/serializer/yaml_serializer/__init__.py
matuamod_serializer/serializer/yaml_serializer/yaml_serilizer.py