Metadata-Version: 2.1
Name: matuamod-serializer
Version: 0.2.2
Summary: My json, toml, yaml serializer/parser library
Home-page: https://github.com/matuamod/ISP-2022-053504/
Author: matuamod
Author-email: matua.models2003@gmail.com
License: MIT
Platform: UNKNOWN
